pydepguard/__init__.py
pydepguard/pylock/__init__.py
pydepguard/pylock/__main__.py
pydepguard/pylock/cache.py
pydepguard/pylock/cli.py
pydepguard/pylock/config.py
pydepguard/pylock/depscan.py
pydepguard/pylock/known_deps.pydepcache
pydepguard/pylock/lockfile.py
pydepguard/pylock/package_handler.py
pydepguard/pylock/resolver.py
pydepguard/pylock/runner.py
pydepguard/pylock/utils.py
pydepguard/pylock/validator.py
pydepguard-3.0.4.dist-info/licenses/LICENSE.md
pydepguard-3.0.4.dist-info/METADATA
pydepguard-3.0.4.dist-info/WHEEL
pydepguard-3.0.4.dist-info/entry_points.txt
pydepguard-3.0.4.dist-info/top_level.txt
pydepguard-3.0.4.dist-info/RECORD
