Metadata-Version: 2.4
Name: pydepguard
Version: 3.0.4
Summary: PyDepGuard PyLock: A gatekeeper dependency validator for Python scripts
Author-email: 0xIkari <zachary@zachary-miller.com>
License: Modified MIT: attribution required for commercial use
Project-URL: Homepage, https://github.com/nuclear-treestump/pylock-dependency-lockfile
Project-URL: Source, https://github.com/nuclear-treestump/pylock-dependency-lockfile
Project-URL: Bug Tracker, https://github.com/nuclear-treestump/pylock-dependency-lockfile/issues
Keywords: dependency,lockfile,security,SBOM,validator,pip,CI
Classifier: License :: Freely Distributable
Classifier: License :: Other/Proprietary License
Classifier: Development Status :: 4 - Beta
Classifier: Programming Language :: Python :: 3.11
Classifier: Intended Audience :: Developers
Classifier: Topic :: Software Development :: Build Tools
Classifier: Topic :: Security
Classifier: Topic :: System :: Systems Administration
Requires-Python: >=3.11
License-File: LICENSE.md
Dynamic: license-file
